pyvaulty-1.5.1.dist-info/licenses/LICENSE
vaulty/__init__.py
vaulty/__main__.py
vaulty/vaulty.py
pyvaulty-1.5.1.dist-info/METADATA
pyvaulty-1.5.1.dist-info/WHEEL
pyvaulty-1.5.1.dist-info/entry_points.txt
pyvaulty-1.5.1.dist-info/top_level.txt
pyvaulty-1.5.1.dist-info/RECORD
