Metadata-Version: 2.4
Name: pyvaulty
Version: 1.5.1
Summary: Encrypt/Decrypt with ChaCha20-Poly1305
Author-email: Chris Mason <chris@netnix.org>
License-Expression: MIT
Project-URL: Repository, https://github.com/cmason3/vaulty.git
Project-URL: Issues, https://github.com/cmason3/vaulty/issues
Classifier: Development Status :: 5 - Production/Stable
Classifier: Programming Language :: Python :: 3
Requires-Python: >=3.10
License-File: LICENSE
Dynamic: license-file
